{
  "Game Dictionary": {
  	"ARTIFACT": {
		"NAMES":[
			"artefato",
			"UNUSED_RESERVE",
			"UNUSED_RESERVE",
			"UNUSED_RESERVE",
			"UNUSED_RESERVE"
		],
		"DESCRIPTION": "Nega o próximo debuff."
	},
	"BLOCK": {
		"NAMES":[
			"proteção",
			"proteções",
			"UNUSED_RESERVE",
			"UNUSED_RESERVE",
			"UNUSED_RESERVE"
		],
		"DESCRIPTION": "Até o próximo turno, previne dano."
	},
	"CURSE": {
		"NAMES":[
			"maldição",
			"UNUSED_RESERVE",
			"UNUSED_RESERVE",
			"UNUSED_RESERVE",
			"UNUSED_RESERVE"
		],
		"DESCRIPTION": "Cartas de maldição são cartas negativas que permanecem no seu baralho."
	},
	"DEXTERITY": {
		"NAMES":[
			"destreza",
			"UNUSED_RESERVE",
			"UNUSED_RESERVE",
			"UNUSED_RESERVE",
			"UNUSED_RESERVE"
		],
		"DESCRIPTION": "Destreza melhora a Proteção ganha de Cartas."
	},
	"ETHEREAL": {
		"NAMES":[
			"etérea",
			"UNUSED_RESERVE",
			"UNUSED_RESERVE",
			"UNUSED_RESERVE",
			"UNUSED_RESERVE"
		],
		"DESCRIPTION": "Se esta carta estiver em sua mão no final do turno, ela será exaurida. Cartas exauridas são removidas do seu baralho até o final do combate."
	},
	"EXHAUST": {
		"NAMES":[
			"exaurir",
			"exaurida",
			"UNUSED_RESERVE",
			"UNUSED_RESERVE",
			"UNUSED_RESERVE"
		],
		"DESCRIPTION": "Removida até o final do combate."
	},
	"INNATE": {
		"NAMES":[
			"inata",
			"UNUSED_RESERVE",
			"UNUSED_RESERVE",
			"UNUSED_RESERVE",
			"UNUSED_RESERVE"
		],
		"DESCRIPTION": "Comece cada combate com esta carta em sua mão."
	},
	"LOCKED": {
		"NAMES":[
			"bloqueada",
			"UNUSED_RESERVE",
			"UNUSED_RESERVE",
			"UNUSED_RESERVE",
			"UNUSED_RESERVE"
		],
		"DESCRIPTION": "Esta carta ainda deve ser desbloqueada."
	},
	"POISON": {
		"NAMES":[
			"veneno",
			"envenenado",
			"UNUSED_RESERVE",
			"UNUSED_RESERVE",
			"UNUSED_RESERVE"
		],
		"DESCRIPTION": "Criaturas envenenadas perdem PV no começo de seus turnos. A cada turno, o Veneno é reduzido em #b1."
	},
	"RETAIN": {
		"NAMES":[
			"manter",
			"mantenha",
			"UNUSED_RESERVE",
			"UNUSED_RESERVE",
			"UNUSED_RESERVE"
		],
		"DESCRIPTION": "Cartas mantidas não são descartadas no final do turno."
	},
	"SHIV": {
		"NAMES":[
			"estoque",
			"estoques",
			"UNUSED_RESERVE",
			"UNUSED_RESERVE",
			"UNUSED_RESERVE"
		],
		"DESCRIPTION": "Estoques são cartas de Ataque com custo #b0 que Exaurem."
	},
	"STATUS": {
		"NAMES":[
			"condição",
			"UNUSED_RESERVE",
			"UNUSED_RESERVE",
			"UNUSED_RESERVE",
			"UNUSED_RESERVE"
		],
		"DESCRIPTION": "Cartas de condição são removidas no final do combate."
	},
	"STRENGTH": {
		"NAMES":[
			"força",
			"UNUSED_RESERVE",
			"UNUSED_RESERVE",
			"UNUSED_RESERVE",
			"UNUSED_RESERVE"
		],
		"DESCRIPTION": "Força adiciona dano adicional a Ataques."
	},
	"TRANSFORM": {
		"NAMES":[
			"transformar",
			"UNUSED_RESERVE",
			"UNUSED_RESERVE",
			"UNUSED_RESERVE",
			"UNUSED_RESERVE"
		],
		"DESCRIPTION": "Cartas transformadas se tornam cartas aleatórias de qualquer raridade."
	},
	"UNKNOWN": {
		"NAMES":[
			"desconhecida",
			"UNUSED_RESERVE",
			"UNUSED_RESERVE",
			"UNUSED_RESERVE",
			"UNUSED_RESERVE"
		],
		"DESCRIPTION": "Essa carta ainda não foi encontrada."
	},
	"UNPLAYABLE": {
		"NAMES":[
			"injogável",
			"UNUSED_RESERVE",
			"UNUSED_RESERVE",
			"UNUSED_RESERVE",
			"UNUSED_RESERVE"
		],
		"DESCRIPTION": "Cartas injogáveis não podem ser jogadas da sua mão."
	},
	"UPGRADE": {
		"NAMES":[
			"aprimorar",
			"UNUSED_RESERVE",
			"UNUSED_RESERVE",
			"UNUSED_RESERVE",
			"UNUSED_RESERVE"
		],
		"DESCRIPTION": "Aprimorar cartas as fazem mais poderosas. Cartas só podem ser aprimoradas uma vez."
	},
	"VULNERABLE": {
		"NAMES":[
			"vulnerável",
			"vulnerabilidade",
			"UNUSED_RESERVE",
			"UNUSED_RESERVE",
			"UNUSED_RESERVE"
		],
		"DESCRIPTION": "Criaturas vulneráveis recebem #b50% a mais de dano de Ataques."
	},
	"WEAK": {
		"NAMES":[
			"fraqueza",
			"enfraquecer",
			"enfraquecido",
			"enfraquece",
			"UNUSED_RESERVE"
		],
		"DESCRIPTION": "Criaturas enfraquecidas causam #b25% a menos de dano em Ataques."
	},
	"WOUND": {
		"NAMES":[
			"ferida",
			"feridas",
			"UNUSED_RESERVE",
			"UNUSED_RESERVE",
			"UNUSED_RESERVE"
		],
		"DESCRIPTION": "Feridas são cartas de condição injogáveis."
	},
	"FRAIL": {
		"NAMES":[
			"fragilizado",
			"UNUSED_RESERVE",
			"UNUSED_RESERVE",
			"UNUSED_RESERVE",
			"UNUSED_RESERVE"
		],
		"DESCRIPTION": "Enquanto Fragilizado, ganhe #b25% menos #yProteção de cartas."
	},
	"STRIKE": {
		"NAMES":[
			"golpe",
			"UNUSED_RESERVE",
			"UNUSED_RESERVE",
			"UNUSED_RESERVE",
			"UNUSED_RESERVE"
		],
		"DESCRIPTION": "Qualquer carta que contenha \"Golpe\" em seu nome."
	},
	"CONFUSED": {
		"NAMES":[
			"confuso",
			"UNUSED_RESERVE",
			"UNUSED_RESERVE",
			"UNUSED_RESERVE",
			"UNUSED_RESERVE"
		],
		"DESCRIPTION": "Sempre que você comprar uma carta, aleatorize seu custo."
	},
	"FIRE": {
		"NAMES":[
			"fire",
			"fired",
			"DONT TRANSLATE FIRED STUFF",
			"DONT TRANSLATE FIRED STUFF",
			"DONT TRANSLATE FIRED STUFF"
		],
		"DESCRIPTION": "Only Ammo can be fired. Firing Ammo activates its effect and discards it."
	},
	"TODO": {
		"NAMES":[
			"todo",
			"JUST FOR DEVS, DONT TRANSLATE",
			"JUST FOR DEVS, DONT TRANSLATE",
			"JUST FOR DEVS, DONT TRANSLATE",
			"JUST FOR DEVS, DONT TRANSLATE"
		],
		"DESCRIPTION": "This card is NOT IMPLEMENTED. Someone should really fix that..."
	},
    "TEXT": [
		"Energia é utilizada para jogar cartas da sua mão."
	]
  }
}
