{
  "Cursed Run": {
    "NAME": "Ukleti pohod",
    "DESCRIPTION": "Svaki put kada poraziš vožda, postaješ uklet. Tvoja urođena relikvija je zamenjena ukletim ključem, tamnokamen amajlijom, i du-vu lutkicom."
  },
  "Elite Swarm": {
    "NAME": "Krupna divljač",
    "DESCRIPTION": "Čelnici su preplavili Toranj, i sada ispuštaju bolje nagrade."
  },
  "Heirloom": {
    "NAME": "Nasledstvo",
    "DESCRIPTION": "Počinješ sa jednom retkom relikvijom."
  },
  "Lethality": {
    "NAME": "Ubojitost",
    "DESCRIPTION": "Svaku borbu započinješ sa snagom povećanom za tri. Isto važi i za neprijatelje."
  },
  "Night Terrors": {
    "NAME": "Noćni strahovi",
    "DESCRIPTION": "Odmaranje u potpunosti zalečuje, ali košta pet maks. ž. p."
  },
  "Insanity": {
    "NAME": "Ludilo",
    "DESCRIPTION": "Počinješ sa špilom od 50 nasumičnih karata."
  },
  "Shiny": {
    "NAME": "Šljašt",
    "DESCRIPTION": "Početni špil je zamenjen sa po jednom od svake retke karte."
  },
  "Allstar": {
    "NAME": "As",
    "DESCRIPTION": "Počinješ sa pet bezbojnih karata."
  },
  "Diverse": {
    "NAME": "Raznovrsnost",
    "DESCRIPTION": "Nisi ograničen samo na karte svog lika."
  },
  "Uncertain Future": {
    "NAME": "Sigurna budućnost",
    "DESCRIPTION": "Mapa sadrži samo jednu putanju."
  },
  "Binary": {
    "NAME": "Binarnost",
    "DESCRIPTION": "Pri biranju nagrade u izboru imaš samo dve karte."
  },
  "Midas": {
    "NAME": "Mida",
    "DESCRIPTION": "Neprijatelji ispuštaju 200% više zlata, ali ne možeš da poboljšaš karte na odmaralištima."
  },
  "Terminal": {
    "NAME": "Jednom nogom u grobu",
    "DESCRIPTION": "Svaki put kada uđeš u novu sobu, gubiš jedan maks. ž. p. Svaku borbu počinješ sa pet optočenog oklopa."
  },
  "Time Dilation": {
    "NAME": "Vremenska dilatacija",
    "DESCRIPTION": "Svi neprijatelji počinju borbu usporeni."
  },
  "Hoarder": {
    "NAME": "Nagomilavanje",
    "DESCRIPTION": "Svaki put kada dodaš kartu u špil, ubaci još dve kopije. Više ne možeš da uklanjaš karte kod trgovca."
  },
  "Vintage": {
    "NAME": "Starina",
    "DESCRIPTION": "Normalni neprijatelji ispuštaju relikvije umesto karata."
  },
  "Draft": {
    "NAME": "Nacrt",
    "DESCRIPTION": "Sastavi početni špil od ponuđenih karata."
  }
}